cottontail/__init__.py
cottontail/base.py
cottontail/errors.py
cottontail/pubsub.py
cottontail/queue.py
cottontail/rpc.py
cottontail/topic.py
cottontail/utils.py
cottontail-0.1a.dist-info/DESCRIPTION.rst
cottontail-0.1a.dist-info/METADATA
cottontail-0.1a.dist-info/metadata.json
cottontail-0.1a.dist-info/RECORD
cottontail-0.1a.dist-info/top_level.txt
cottontail-0.1a.dist-info/WHEEL
